{
  "Territory 2025": {
    "name": "Territory 2025",
    "own": {
      "vehicleid_key": "FORD_TERRITORY_TITANIUM FWD 1.8L_2025",
      "make": "FORD",
      "model": "TERRITORY",
      "version": "TITANIUM FWD 1.8L",
      "ano": 2025,
      "msrp": 773500,
      "precio_transaccion": 673500,
      "longitud_mm": 4625,
      "body_style": "todo terreno",
      "categoria_combustible_final": "premium",
      "tipo_hybrid": false,
      "mot_tipo_motor": "",
      "bateria_kwh": "",
      "driven_wheels": "fwd",
      "traccion_original": "delantera",
      "mot_potencia_hp": "",
      "seg_act_esp": "",
      "info_apple_carplay": "",
      "info_android_auto": "",
      "adas_aeb": "",
      "ventas_modelo": ""
    },
    "competitors": [
      {
        "vehicleid_key": "BYD_SONG PLUS_DM-I 115KM_2025",
        "make": "BYD",
        "model": "SONG PLUS",
        "version": "DM-I 115KM",
        "ano": 2025,
        "msrp": 778800,
        "precio_transaccion": 778800,
        "longitud_mm": 4775,
        "body_style": "todo terreno",
        "categoria_combustible_final": "electrico",
        "tipo_hybrid": false,
        "mot_tipo_motor": "",
        "bateria_kwh": "",
        "driven_wheels": "fwd",
        "traccion_original": "delantera",
        "mot_potencia_hp": "",
        "seg_act_esp": "",
        "info_apple_carplay": "",
        "info_android_auto": "",
        "adas_aeb": "",
        "ventas_modelo": ""
      },
      {
        "vehicleid_key": "VOLKSWAGEN_TIGUAN_R-LINE 1.4_2025",
        "make": "VOLKSWAGEN",
        "model": "TIGUAN",
        "version": "R-LINE 1.4",
        "ano": 2025,
        "msrp": 771990,
        "precio_transaccion": 771990,
        "longitud_mm": 4670,
        "body_style": "todo terreno",
        "categoria_combustible_final": "premium",
        "tipo_hybrid": false,
        "mot_tipo_motor": "",
        "bateria_kwh": "",
        "driven_wheels": "fwd",
        "traccion_original": "delantera",
        "mot_potencia_hp": "",
        "seg_act_esp": "",
        "info_apple_carplay": "",
        "info_android_auto": "",
        "adas_aeb": "",
        "ventas_modelo": ""
      },
      {
        "vehicleid_key": "HONDA_CR-V_TOURING_2025",
        "make": "HONDA",
        "model": "CR-V",
        "version": "TOURING",
        "ano": 2025,
        "msrp": 858900,
        "precio_transaccion": 833900,
        "longitud_mm": 4695,
        "body_style": "todo terreno",
        "categoria_combustible_final": "premium",
        "tipo_hybrid": false,
        "mot_tipo_motor": "",
        "bateria_kwh": "",
        "driven_wheels": "fwd",
        "traccion_original": "delantera",
        "mot_potencia_hp": "",
        "seg_act_esp": "",
        "info_apple_carplay": "",
        "info_android_auto": "",
        "adas_aeb": "",
        "ventas_modelo": 1864
      },
      {
        "vehicleid_key": "MAZDA_CX-5_SIGNATURE 2WD_2025",
        "make": "MAZDA",
        "model": "CX-5",
        "version": "SIGNATURE 2WD",
        "ano": 2025,
        "msrp": 681900,
        "precio_transaccion": 681900,
        "longitud_mm": 4575,
        "body_style": "todo terreno",
        "categoria_combustible_final": "magna",
        "tipo_hybrid": false,
        "mot_tipo_motor": "",
        "bateria_kwh": "",
        "driven_wheels": "fwd",
        "traccion_original": "delantera",
        "mot_potencia_hp": "",
        "seg_act_esp": "",
        "info_apple_carplay": "",
        "info_android_auto": "",
        "adas_aeb": "",
        "ventas_modelo": 2195
      },
      {
        "vehicleid_key": "TOYOTA_RAV4_LTD_2025",
        "make": "TOYOTA",
        "model": "RAV4",
        "version": "LTD",
        "ano": 2025,
        "msrp": 742100,
        "precio_transaccion": 742100,
        "longitud_mm": 4600,
        "body_style": "todo terreno",
        "categoria_combustible_final": "magna",
        "tipo_hybrid": false,
        "mot_tipo_motor": "",
        "bateria_kwh": "",
        "driven_wheels": "4wd",
        "traccion_original": "4x4",
        "mot_potencia_hp": "",
        "seg_act_esp": "",
        "info_apple_carplay": "",
        "info_android_auto": "",
        "adas_aeb": "",
        "ventas_modelo": 1825
      }
    ],
    "updated_at": 1757356041
  }
}